LICENSE
MANIFEST.in
README.MD
setup.py
hmd/__init__.py
hmd/__main__.py
hmd/hmd.py
hmd.egg-info/PKG-INFO
hmd.egg-info/SOURCES.txt
hmd.egg-info/dependency_links.txt
hmd.egg-info/entry_points.txt
hmd.egg-info/top_level.txt