Metadata-Version: 2.1
Name: hmd
Version: 0.7
Summary: Simple markdown language and processor for write and render document similar to man pages, from command line or from Python
Home-page: https://github.com/Docheinstein/hmd
Author: Stefano Dottore
Author-email: docheinstein@gmail.com
License: MIT
Keywords: hmd
Platform: UNKNOWN
Requires-Python: >=3.5
